Workbook

Sheet Controle
A1: ID | B1: Reagente | C1: Data | D1: Para quem | E1: Observação | F1: Preço (R$) | G1: Total pago (R$) | H1: Saldo em aberto (R$) | I1: Status | J1: Forma de compra
A2: 1 | B2: ph34 | C2: 46276 | D2: Biolab | E2: O produto foi selecionado, pois atende às especificações do imetro | F2: 206.45 | G2: =IF(B2="","",SUMIF(Pagamentos!$B$2:$B$1001,A2,Pagamentos!$D$2:$D$1001)) | H2: =IF(B2="","",MAX(F2-G2,0)) | I2: =IF(B2="","",IF(H2<=0,"PAGO",IF(G2>0,"PARCIAL","PENDENTE"))) | J2: À vista
A3: 2 | B3: cloreto de potássio | C3: 46270 | D3: JetLab | E3: O produto é o único com as especificações técnicas necessárias. | F3: 134.67 | G3: =IF(B3="","",SUMIF(Pagamentos!$B$2:$B$1001,A3,Pagamentos!$D$2:$D$1001)) | H3: =IF(B3="","",MAX(F3-G3,0)) | I3: =IF(B3="","",IF(H3<=0,"PAGO",IF(G3>0,"PARCIAL","PENDENTE"))) | J3: FAPEMIG - reembolso integral
A4: 3 | G4: =IF(B4="","",SUMIF(Pagamentos!$B$2:$B$1001,A4,Pagamentos!$D$2:$D$1001)) | H4: =IF(B4="","",MAX(F4-G4,0)) | I4: =IF(B4="","",IF(H4<=0,"PAGO",IF(G4>0,"PARCIAL","PENDENTE")))
A5: 4 | G5: =IF(B5="","",SUMIF(Pagamentos!$B$2:$B$1001,A5,Pagamentos!$D$2:$D$1001)) | H5: =IF(B5="","",MAX(F5-G5,0)) | I5: =IF(B5="","",IF(H5<=0,"PAGO",IF(G5>0,"PARCIAL","PENDENTE")))
A6: 5 | G6: =IF(B6="","",SUMIF(Pagamentos!$B$2:$B$1001,A6,Pagamentos!$D$2:$D$1001)) | H6: =IF(B6="","",MAX(F6-G6,0)) | I6: =IF(B6="","",IF(H6<=0,"PAGO",IF(G6>0,"PARCIAL","PENDENTE")))
A7: 6 | G7: =IF(B7="","",SUMIF(Pagamentos!$B$2:$B$1001,A7,Pagamentos!$D$2:$D$1001)) | H7: =IF(B7="","",MAX(F7-G7,0)) | I7: =IF(B7="","",IF(H7<=0,"PAGO",IF(G7>0,"PARCIAL","PENDENTE")))
A8: 7 | G8: =IF(B8="","",SUMIF(Pagamentos!$B$2:$B$1001,A8,Pagamentos!$D$2:$D$1001)) | H8: =IF(B8="","",MAX(F8-G8,0)) | I8: =IF(B8="","",IF(H8<=0,"PAGO",IF(G8>0,"PARCIAL","PENDENTE")))
A9: 8 | G9: =IF(B9="","",SUMIF(Pagamentos!$B$2:$B$1001,A9,Pagamentos!$D$2:$D$1001)) | H9: =IF(B9="","",MAX(F9-G9,0)) | I9: =IF(B9="","",IF(H9<=0,"PAGO",IF(G9>0,"PARCIAL","PENDENTE")))
A10: 9 | G10: =IF(B10="","",SUMIF(Pagamentos!$B$2:$B$1001,A10,Pagamentos!$D$2:$D$1001)) | H10: =IF(B10="","",MAX(F10-G10,0)) | I10: =IF(B10="","",IF(H10<=0,"PAGO",IF(G10>0,"PARCIAL","PENDENTE")))
A11: 10 | G11: =IF(B11="","",SUMIF(Pagamentos!$B$2:$B$1001,A11,Pagamentos!$D$2:$D$1001)) | H11: =IF(B11="","",MAX(F11-G11,0)) | I11: =IF(B11="","",IF(H11<=0,"PAGO",IF(G11>0,"PARCIAL","PENDENTE")))
A12: 11 | G12: =IF(B12="","",SUMIF(Pagamentos!$B$2:$B$1001,A12,Pagamentos!$D$2:$D$1001)) | H12: =IF(B12="","",MAX(F12-G12,0)) | I12: =IF(B12="","",IF(H12<=0,"PAGO",IF(G12>0,"PARCIAL","PENDENTE")))
A13: 12 | G13: =IF(B13="","",SUMIF(Pagamentos!$B$2:$B$1001,A13,Pagamentos!$D$2:$D$1001)) | H13: =IF(B13="","",MAX(F13-G13,0)) | I13: =IF(B13="","",IF(H13<=0,"PAGO",IF(G13>0,"PARCIAL","PENDENTE")))
A14: 13 | G14: =IF(B14="","",SUMIF(Pagamentos!$B$2:$B$1001,A14,Pagamentos!$D$2:$D$1001)) | H14: =IF(B14="","",MAX(F14-G14,0)) | I14: =IF(B14="","",IF(H14<=0,"PAGO",IF(G14>0,"PARCIAL","PENDENTE")))
A15: 14 | G15: =IF(B15="","",SUMIF(Pagamentos!$B$2:$B$1001,A15,Pagamentos!$D$2:$D$1001)) | H15: =IF(B15="","",MAX(F15-G15,0)) | I15: =IF(B15="","",IF(H15<=0,"PAGO",IF(G15>0,"PARCIAL","PENDENTE")))
... A301: 300 | G301: =IF(B301="","",SUMIF(Pagamentos!$B$2:$B$1001,A301,Pagamentos!$D$2:$D$1001)) | H301: =IF(B301="","",MAX(F301-G301,0)) | I301: =IF(B301="","",IF(H301<=0,"PAGO",IF(G301>0,"PARCIAL","PENDENTE")))

Sheet Pagamentos
A1: ID Pagamento | B1: ID do item | C1: Data do pagamento | D1: Valor pago (R$) | E1: Observação
A2: 1 | B2: 1 | C2: 46276 | D2: 206.45 | E2: pago
A3: 2
A4: 3
A5: 4
A6: 5
A7: 6
A8: 7
A9: 8
A10: 9
A11: 10
A12: 11
A13: 12
A14: 13
... A1001: 1000

Sheet Resumo
A1: RESUMO FINANCEIRO - LABORATÓRIO 217
A3: Indicador | B3: Valor
A4: Total das compras | B4: =SUM(Controle!F2:F301)
A5: Total pago | B5: =SUM(Controle!G2:G301)
A6: Dívida atual | B6: =SUM(Controle!H2:H301)
A7: Itens pendentes | B7: =COUNTIF(Controle!I2:I301,"PENDENTE")
A8: Itens parcialmente pagos | B8: =COUNTIF(Controle!I2:I301,"PARCIAL")
A10: Como funciona
A11: 1 | B11: Cadastre o item na aba Controle. O ID já existe e não precisa ser digitado.
A12: 2 | B12: Registre cada pagamento na aba Pagamentos usando o ID do item. O saldo e o status são atualizados automaticamente.
A13: 3 | B13: Quando o saldo chega a zero, o status vira PAGO e o item deixa de compor a dívida atual.

Sheet Observações
A1: ID | B1: Data | C1: ID do item (opcional) | D1: Observação
A2: 1
A3: 2
A4: 3
A5: 4
A6: 5
A7: 6
A8: 7
A9: 8
A10: 9
A11: 10
A12: 11
A13: 12
... A301: 300
